Workbook

Sheet README
A1: MeTravel — Transport Price Dataset
A2: Phase 0 deliverable: curated transport data for Vietnamese travellers abroad
A4: HOW TO USE THIS FILE
A5: 1. Fill only the YELLOW columns on the 'transport_data' sheet. GREEN columns are formulas — leave them alone.
A6: 2. Row 2 is a filled-in EXAMPLE showing the expected format. Do not delete it; delete it only at the very end.
A7: 3. Update 'rates' sheet with today's exchange rates before you start. VND columns calculate automatically.
A8: 4. Every row needs a source_url. A price with no source is worthless in a portfolio.
A9: 5. Target: 30 rows done well beats 100 rows guessed. Aim for ~10 rows per week for 3 weeks.
A11: COLUMN DEFINITIONS
A12: route_id | B12: Unique ID. Format: CITY-NN, e.g. BKK-01
A13: method_type | B13: One of: metro / train / bus / taxi / ride_hail / private_car / ferry / walk
A14: price_min_local / price_max_local | B14: Range in LOCAL currency. If price is fixed, put the same number in both.
A15: comfort_1_5 | B15: 1 = crowded, standing, no aircon. 5 = private door-to-door car.
A16: luggage_ok | B16: yes / no / tight — can you realistically do this with a 24-inch suitcase?
A17: operates_from / operates_to | B17: 24h format, e.g. 05:30 / 24:00. CRITICAL: cheap flights land late at night.
A18: how_to_buy | B18: Concrete instruction: which counter, which machine, cash or card, what to say.
A19: app_needed | B19: App to install BEFORE departure, e.g. Grab, Kakao T, Suica. Write 'none' if not needed.
A20: language_difficulty_1_5 | B20: How hard is this WITHOUT the local language? 1 = fully English/self-service, 5 = must negotiate verbally.
A21: scam_risk_note | B21: Known overcharge or scam pattern on this route. Blank if none.
A22: last_updated | B22: Date you verified the price. Format YYYY-MM-DD.
A24: WHERE TO FIND PRICES (in order of reliability)
A25: 1. Official operator site — airport, metro, rail company. Best source.
A26: 2. Official tourism board site of the city.
A27: 3. Recent Reddit threads (r/JapanTravel, r/korea, r/Thailand) — filter to last 12 months.
A28: 4. YouTube vlogs from the last year — good for 'how to actually do it' steps.
A29: 5. Vietnamese Facebook groups — good for scam notes, weak for exact prices.
A31: ANALYSIS QUESTIONS THIS DATASET WILL ANSWER (your portfolio piece)
A32: Q1. Which city has the biggest gap between cheapest and most expensive airport transfer?
A33: Q2. What is the 'convenience premium' — how many times more does a taxi cost vs public transport, per city?
A34: Q3. Which cities strand a late-night arrival (no public option after 23:00) and what does that cost?
A35: Q4. Is there a correlation between language_difficulty and price spread? (Does not speaking the language cost money?)
A36: Q5. What is the realistic transport budget in VND for a 5-day trip, by city and by travel style?
... A39: Export 'transport_data' as CSV -> load into SQLite -> answer Q1-Q5 with SQL -> publish to GitHub with charts.

Sheet rates
A1: Exchange rates — UPDATE THESE BEFORE YOU START
A2: Source: xe.com or Google. Re-check monthly. VND columns on transport_data depend on this table.
A4: currency_code | B4: currency_name | C4: vnd_per_unit
A5: THB | B5: Thai Baht | C5: 780
A6: KRW | B6: Korean Won | C6: 19
A7: JPY | B7: Japanese Yen | C7: 175
A8: SGD | B8: Singapore Dollar | C8: 19500
A9: TWD | B9: Taiwan Dollar | C9: 800
A10: USD | B10: US Dollar | C10: 25500
A11: MYR | B11: Malaysian Ringgit | C11: 5900
A12: VND | B12: Vietnamese Dong | C12: 1
A14: Placeholder rates — verify before use.

Sheet transport_data
A1: route_id | B1: city | C1: country | D1: origin | E1: destination | F1: method_type | G1: method_name | H1: currency | I1: price_min_local | J1: price_max_local | K1: price_min_vnd | L1: price_max_vnd | M1: duration_min | N1: duration_max | O1: comfort_1_5 | P1: luggage_ok | Q1: operates_from | R1: operates_to | S1: how_to_buy | T1: app_needed | U1: language_difficulty_1_5 | V1: scam_risk_note | W1: source_url | X1: last_updated | Y1: price_basis
A2: EXAMPLE | B2: Bangkok | C2: Thailand | D2: Suvarnabhumi Airport (BKK) | E2: Sukhumvit / Asok | F2: train | G2: Airport Rail Link (City Line) | H2: THB | I2: 45 | J2: 45 | K2: =IF(I2="","",IFERROR(I2*INDEX(rates!$C$5:$C$12,MATCH($H2,rates!$A$5:$A$12,0)),"check currency code")) -> 35100 | L2: =IF(J2="","",IFERROR(J2*INDEX(rates!$C$5:$C$12,MATCH($H2,rates!$A$5:$A$12,0)),"check currency code")) -> 35100 | M2: 30 | N2: 40 | O2: 3 | P2: tight | Q2: 06:00 | R2: 24:00 | S2: Follow signs to Level B. Buy token at machine or counter, cash THB only. Ride to Phaya Thai, transfer to BTS. | T2: none | U2: 2 | V2: None on the train itself. Taxi touts wait at arrivals — ignore them. | W2: https://www.suvarnabhumiairport.com | X2: 2026-08-24 | Y2: per_person
A3: BKK-01 | B3: Bangkok | C3: Thailand | D3: Suvarnabhumi Airport (BKK) | E3: Sukhumvit / Asok | F3: train | G3: Airport Rail Link (City Line) | H3: THB | I3: 45 | J3: 45 | K3: =IF(I3="","",IFERROR(I3*INDEX(rates!$C$5:$C$12,MATCH($H3,rates!$A$5:$A$12,0)),"check currency code")) -> 35100 | L3: =IF(J3="","",IFERROR(J3*INDEX(rates!$C$5:$C$12,MATCH($H3,rates!$A$5:$A$12,0)),"check currency code")) -> 35100 | M3: 30 | N3: 40 | O3: 3 | P3: tight | Q3: 06:00 | R3: 24:00 | S3: Follow signs to Level B. Buy token at machine or counter, cash THB only. Ride to Phaya Thai, transfer to BTS. | T3: none | U3: 2 | V3: None on the train itself. Taxi touts wait at arrivals — ignore them. | W3: https://suvarnabhumi.airportthai.co.th/service/transportation/detail/304 ; https://bkkairportlink.com/fare | X3: 2026-08-24 | Y3: per_person
A4: BKK-02 | B4: Bangkok | C4: Thailand | D4: Suvarnabhumi Airport (BKK) | E4: Khao San Road | F4: bus | G4: Bus S1 | H4: THB | I4: 60 | J4: 60 | K4: =IF(I4="","",IFERROR(I4*INDEX(rates!$C$5:$C$12,MATCH($H4,rates!$A$5:$A$12,0)),"check currency code")) -> 46800 | L4: =IF(J4="","",IFERROR(J4*INDEX(rates!$C$5:$C$12,MATCH($H4,rates!$A$5:$A$12,0)),"check currency code")) -> 46800 | M4: 60 | N4: 90 | O4: 1 | P4: tight | Q4: 06:00 | R4: 20:00 | S4: Tang 1, canh Gate 7. Len xe roi tra tien mat cho phu xe, gia dong 60 THB bat ke xuong o dau. Khong mua truoc duoc. Tranh dua to 500/1000 THB. | T4: none | U4: 2 | V4: Gia dong, khong the bi chat chem. Rui ro chinh la lo chuyen cuoi luc 20:00. | W4: https://suvarnabhumi.airportthai.co.th/service/transportation/detail/317 | X4: 2026-08-24 | Y4: per_person
A5: BKK-03 | B5: Bangkok | C5: Thailand | D5: Suvarnabhumi Airport (BKK) | E5: Sukhumvit / Asok | F5: taxi | G5: Metered taxi (public rank) | H5: THB | I5: 400 | J5: 600 | K5: =IF(I5="","",IFERROR(I5*INDEX(rates!$C$5:$C$12,MATCH($H5,rates!$A$5:$A$12,0)),"check currency code")) -> 312000 | L5: =IF(J5="","",IFERROR(J5*INDEX(rates!$C$5:$C$12,MATCH($H5,rates!$A$5:$A$12,0)),"check currency code")) -> 468000 | M5: 45 | N5: 60 | O5: 4 | P5: yes | Q5: 00:00 | R5: 24:00 | S5: Tang 1, quay taxi cong cong giua Gate 4-7. Lay phieu o may tu dong, KHONG di theo nguoi moi chao. Yeu cau bat dong ho. | T5: none | U5: 4 | V5: Phu phi san bay 50 THB la HOP LE (theo thong bao Bo GTVT), khong phai chat chem. Phi cao toc ~70 THB khach tu tra tien mat. Chieu 'dong ho hong, di gia tron goi' la lua dao. | W5: https://suvarnabhumi.airportthai.co.th/service/transportation/detail/304 | X5: 2026-08-24 | Y5: per_vehicle
A6: BKK-04 | B6: Bangkok | C6: Thailand | D6: Suvarnabhumi Airport (BKK) | E6: Sukhumvit / Asok | F6: ride_hail | G6: Grab | H6: THB | I6: 450 | J6: 700 | K6: =IF(I6="","",IFERROR(I6*INDEX(rates!$C$5:$C$12,MATCH($H6,rates!$A$5:$A$12,0)),"check currency code")) -> 351000 | L6: =IF(J6="","",IFERROR(J6*INDEX(rates!$C$5:$C$12,MATCH($H6,rates!$A$5:$A$12,0)),"check currency code")) -> 546000 | M6: 45 | N6: 60 | O6: 4 | P6: yes | Q6: 00:00 | R6: 24:00 | S6: Cai app Grab truoc khi bay, dung tai khoan Viet Nam duoc. Ra diem don Grab rieng cua san bay theo bien chi dan, khong ra quay taxi. Gia hien san trong app truoc khi dat. | T6: Grab | U6: 1 | V6: Gia chot trong app, khong mac ca. Nhung 01:00-04:00 rat kho goi duoc tai xe. Gia dong theo nhu cau nen co the cao hon taxi dong ho vao gio cao diem. | W6: https://www.faditaxi.com/airport/suvarnabhumi-airport-taxi ; https://www.thaizer.com/how-to-catch-a-taxi-from-bangkok-airport/ | X6: 2026-08-24 | Y6: per_vehicle
A7: BKK-05 | B7: Bangkok | C7: Thailand | D7: Suvarnabhumi Airport (BKK) | E7: Sukhumvit / Asok | F7: private_car | G7: Pre-booked private transfer | H7: THB | I7: 800 | J7: 1200 | K7: =IF(I7="","",IFERROR(I7*INDEX(rates!$C$5:$C$12,MATCH($H7,rates!$A$5:$A$12,0)),"check currency code")) -> 624000 | L7: =IF(J7="","",IFERROR(J7*INDEX(rates!$C$5:$C$12,MATCH($H7,rates!$A$5:$A$12,0)),"check currency code")) -> 936000 | M7: 45 | N7: 60 | O7: 5 | P7: yes | Q7: 00:00 | R7: 24:00 | S7: Dat truoc online (Klook, Trip.com hoac cong ty transfer) truoc ngay bay. Tai xe cam bien ten don tai sanh den. Gia chot truoc, khong phat sinh phi cao toc. | T7: none | U7: 1 | V7: Gia co dinh, khong co rui ro chat chem. Doi lai la dat nhat. Dang tien khi di nhom 3-4 nguoi hoac ha canh ban dem. | W7: https://www.thaizer.com/how-to-catch-a-taxi-from-bangkok-airport/ | X7: 2026-08-24 | Y7: per_vehicle
A8: DMK-01 | B8: Bangkok | C8: Thailand | D8: Don Mueang Airport (DMK) | E8: Mo Chit BTS | F8: bus | G8: Bus A1 | H8: THB | I8: 30 | J8: 30 | K8: =IF(I8="","",IFERROR(I8*INDEX(rates!$C$5:$C$12,MATCH($H8,rates!$A$5:$A$12,0)),"check currency code")) -> 23400 | L8: =IF(J8="","",IFERROR(J8*INDEX(rates!$C$5:$C$12,MATCH($H8,rates!$A$5:$A$12,0)),"check currency code")) -> 23400 | M8: 23 | N8: 45 | O8: 2 | P8: tight | Q8: 05:45 | R8: 24:00 | S8: Ra Cua so 6, sanh den Terminal 1, tim bien 'BMTA Bus'. Len xe roi tra tien mat truc tiep cho phu xe, gia dong 30 THB bat ke xuong dau. Chuan bi tien le, tranh dua to. | T8: none | U8: 3 | V8: Gia dong nen khong the bi chat chem. Cho de hanh ly tren xe han che, gio cao diem co the phai dung suot chang. | W8: https://donmueang.airportthai.co.th/service/transportation/detail/205 ; https://www.thaizer.com/airport-bus-service-to-and-from-bangkok-don-muang/ | X8: 2026-08-24 | Y8: per_person
A9: DMK-02 | B9: Bangkok | C9: Thailand | D9: Don Mueang Airport (DMK) | E9: Bang Sue Grand Station | F9: train | G9: SRT Red Line | H9: THB | I9: 33 | J9: 33 | K9: =IF(I9="","",IFERROR(I9*INDEX(rates!$C$5:$C$12,MATCH($H9,rates!$A$5:$A$12,0)),"check currency code")) -> 25740 | L9: =IF(J9="","",IFERROR(J9*INDEX(rates!$C$5:$C$12,MATCH($H9,rates!$A$5:$A$12,0)),"check currency code")) -> 25740 | M9: 17 | N9: 20 | O9: 3 | P9: tight | Q9: 05:30 | R9: 24:00 | S9: Co skywalk noi thang tu san bay sang ga. Mua token o may tu dong hoac quay co nhan vien, CHI nhan tien mat THB. Quet token o cua soat ve. Ve SRT khong dung duoc cho MRT/BTS - phai mua ve rieng neu di tiep. | T9: none | U9: 2 | V9: Gia niem yet, khong co rui ro. Luu y: den Bang Sue van phai doi sang MRT moi vao trung tam. | W9: https://www.renown-travel.com/daytripsbangkok/srtredline.html ; https://thaiest.com/thailand/bangkok/srt-red-line | X9: 2026-08-24 | Y9: per_person
A10: DMK-03 | B10: Bangkok | C10: Thailand | D10: Don Mueang Airport (DMK) | E10: Khao San Road | F10: taxi | G10: Metered taxi (public rank) | H10: THB | I10: 400 | J10: 500 | K10: =IF(I10="","",IFERROR(I10*INDEX(rates!$C$5:$C$12,MATCH($H10,rates!$A$5:$A$12,0)),"check currency code")) -> 312000 | L10: =IF(J10="","",IFERROR(J10*INDEX(rates!$C$5:$C$12,MATCH($H10,rates!$A$5:$A$12,0)),"check currency code")) -> 390000 | M10: 20 | N10: 30 | O10: 4 | P10: yes | Q10: 00:00 | R10: 24:00 | S10: Quay taxi o Terminal 1 quoc te tang 1 canh Gate 8, hoac Terminal 2 noi dia canh Gate 15. Lay phieu tai quay, khong di theo nguoi moi chao. Yeu cau bat dong ho. | T10: none | U10: 4 | V10: Phu phi san bay 50 THB cong vao dong ho la HOP LE theo thong bao Bo GTVT Thai Lan, khong phai chat chem. Phi duong cao toc khach tu tra tien mat tai tram. | W10: https://donmueang.airportthai.co.th/service/transportation/detail/211 | X10: 2026-08-24 | Y10: per_vehicle
A11: ICN-01 | B11: Seoul | C11: South Korea | D11: Incheon Airport T1 (ICN) | E11: Seoul Station | F11: train | G11: AREX Express Train | H11: KRW | I11: 11500 | J11: 13000 | K11: =IF(I11="","",IFERROR(I11*INDEX(rates!$C$5:$C$12,MATCH($H11,rates!$A$5:$A$12,0)),"check currency code")) -> 218500 | L11: =IF(J11="","",IFERROR(J11*INDEX(rates!$C$5:$C$12,MATCH($H11,rates!$A$5:$A$12,0)),"check currency code")) -> 247000 | M11: 43 | N11: 51 | O11: 4 | P11: yes | Q11: 05:15 | R11: 22:40 | S11: Mua ở quầy Express Train hoặc máy tự động tại ga sân bay. Máy thường từ chối thẻ nước ngoài — nếu vậy ra quầy thanh toán bằng thẻ. Vé có ghế ngồi cố định, có khoang để vali riêng. | T11: none | U11: 2 | V11: Gia niem yet 13.000 KRW tai quay, khoang 11.500 KRW neu mua online truoc. Ve Express dung he thong soat ve rieng - KHONG chuyen tuyen mien phi sang tau thuong. Lo chuyen phai ra quay doi ve va tra phi phat 3.500 KRW. | W11: https://www.theseoulguide.com/airport-railroad-arex-express-train/ | X11: 2026-08-24 | Y11: per_person
A12: ICN-02 | B12: Seoul | C12: South Korea | D12: Incheon Airport T1 (ICN) | E12: Hongdae | F12: train | G12: AREX All-Stop Train | H12: KRW | I12: 4150 | J12: 4150 | K12: =IF(I12="","",IFERROR(I12*INDEX(rates!$C$5:$C$12,MATCH($H12,rates!$A$5:$A$12,0)),"check currency code")) -> 78850 | L12: =IF(J12="","",IFERROR(J12*INDEX(rates!$C$5:$C$12,MATCH($H12,rates!$A$5:$A$12,0)),"check currency code")) -> 78850 | M12: 59 | N12: 66 | O12: 2 | P12: tight | Q12: 05:20 | R12: 23:38 | S12: Mua token o may tu dong tai ga, hoac quet the T-money. Nen mua the T-money o cua hang tien loi trong san bay truoc - the ngan hang nuoc ngoai khong quet truc tiep duoc o cua soat ve. | T12: none | U12: 2 | V12: Gia theo cu ly, toi da khoang 5.350 KRW. Uu diem it ai biet: tau nay dung thang o ga Hongik University, con Express chay qua khong dung - neu o Hongdae thi tau re hon lai tien hon. | W12: https://creatrip.com/en/blog/1696 | X12: 2026-08-24 | Y12: per_person
A13: ICN-03 | B13: Seoul | C13: South Korea | D13: Incheon Airport T1 (ICN) | E13: Myeongdong | F13: bus | G13: Limousine Bus 6015 | H13: KRW | I13: 17000 | J13: 17000 | K13: =IF(I13="","",IFERROR(I13*INDEX(rates!$C$5:$C$12,MATCH($H13,rates!$A$5:$A$12,0)),"check currency code")) -> 323000 | L13: =IF(J13="","",IFERROR(J13*INDEX(rates!$C$5:$C$12,MATCH($H13,rates!$A$5:$A$12,0)),"check currency code")) -> 323000 | M13: 60 | N13: 90 | O13: 4 | P13: yes | Q13: 05:20 | R13: 22:50 | S13: Mua ve o quay hoac kiosk trong sanh den TRUOC khi ra ben - chieu tu san bay KHONG quet T-money len xe duoc. Kiosk nhan the nuoc ngoai. Hanh ly de duoi gam xe, nhan viec xep giup. | T13: none | U13: 2 | V13: Gia co dinh 17.000 KRW, khong co rui ro. Rui ro that la tac duong - tranh khung 16:30-19:30. Bu lai xe do ngay truoc nhieu khach san, khong phai keo vali qua cau thang ga tau. | W13: https://askkoreatravel.com/mastering-the-6015-airport-bus-the/ | X13: 2026-08-24 | Y13: per_person
... A19: SIN-04 | B19: Singapore | C19: Singapore | D19: Changi Airport (SIN) | E19: Bugis | F19: ride_hail | G19: Grab | H19: SGD | I19: 22 | J19: 45 | K19: =IF(I19="","",IFERROR(I19*INDEX(rates!$C$5:$C$12,MATCH($H19,rates!$A$5:$A$12,0)),"check currency code")) -> 429000 | L19: =IF(J19="","",IFERROR(J19*INDEX(rates!$C$5:$C$12,MATCH($H19,rates!$A$5:$A$12,0)),"check currency code")) -> 877500 | M19: 25 | N19: 40 | O19: 4 | P19: yes | Q19: 00:00 | R19: 24:00 | S19: Cai app Grab truoc khi bay, tai khoan Viet Nam dung duoc. Ra diem don ride-hail rieng theo bien chi dan. Gia hien day du truoc khi dat. | T19: Grab | U19: 1 | V19: Gia chot trong app, da bao gom moi phu phi. Nhung tang gia dong khi mua hoac gio cao diem - co the vot len gap doi. Neu thay gia cao, doi 10-15 phut hoac di MRT vao trung tam roi goi Grab chang ngan. | W19: https://www.singapore-spirit.com/guides/grab-taxis-singapore/ ; https://www.travelarbitrage.net/en/blog/singapore-airport-transfer-backpacker-rainy-season-budget-2026/ | X19: 2026-08-24 | Y19: per_vehicle
